magictypes/__init__.py
magictypes/__main__.py
magictypes/file.py
magictypes-0.8.0.dist-info/METADATA
magictypes-0.8.0.dist-info/WHEEL
magictypes-0.8.0.dist-info/RECORD
